autodistill_azure_vision/__init__.py
autodistill_azure_vision/azure_vision_model.py
autodistill_azure_vision-0.1.0.dist-info/LICENSE
autodistill_azure_vision-0.1.0.dist-info/METADATA
autodistill_azure_vision-0.1.0.dist-info/WHEEL
autodistill_azure_vision-0.1.0.dist-info/top_level.txt
autodistill_azure_vision-0.1.0.dist-info/RECORD
